DisFlood/DisFlood.py
DisFlood/__init__.py
DisFlood-1.3.2.dist-info/METADATA
DisFlood-1.3.2.dist-info/WHEEL
DisFlood-1.3.2.dist-info/top_level.txt
DisFlood-1.3.2.dist-info/RECORD
