Metadata-Version: 2.1
Name: DisFlood
Version: 1.3.2
Summary: This library for flood to discord
Home-page: UNKNOWN
Author: Lcvb_X
Author-email: podygka1990@gmail.com
License: UNKNOWN
Platform: UNKNOWN
Classifier: Programming Language :: Python :: 3
Classifier: License :: OSI Approved :: MIT License
Classifier: Operating System :: OS Independent
Requires-Python: >=3.6
